ppasr/__init__.py
ppasr/predict.py
ppasr/trainer.py
ppasr/configs/augmentation.yml
ppasr/configs/conformer.yml
ppasr/configs/decoder.yml
ppasr/configs/deepspeech2.yml
ppasr/configs/efficient_conformer.yml
ppasr/configs/squeezeformer.yml
ppasr/data_utils/__init__.py
ppasr/data_utils/audio_featurizer.py
ppasr/data_utils/binary.py
ppasr/data_utils/collate_fn.py
ppasr/data_utils/normalizer.py
ppasr/data_utils/reader.py
ppasr/data_utils/sampler.py
ppasr/data_utils/tokenizer.py
ppasr/data_utils/utils.py
ppasr/decoders/__init__.py
ppasr/decoders/attention_rescoring.py
ppasr/decoders/beam_search_decoder.py
ppasr/decoders/ctc_greedy_search.py
ppasr/decoders/ctc_prefix_beam_search.py
ppasr/decoders/utils.py
ppasr/infer_utils/__init__.py
ppasr/infer_utils/decoder_predictor.py
ppasr/infer_utils/encoder_predictor.py
ppasr/infer_utils/punc_predictor.py
ppasr/infer_utils/streaming_encoder_predictor.py
ppasr/infer_utils/utils.py
ppasr/model_utils/__init__.py
ppasr/model_utils/conformer/__init__.py
ppasr/model_utils/conformer/attention.py
ppasr/model_utils/conformer/convolution.py
ppasr/model_utils/conformer/embedding.py
ppasr/model_utils/conformer/encoder.py
ppasr/model_utils/conformer/model.py
ppasr/model_utils/conformer/positionwise.py
ppasr/model_utils/conformer/subsampling.py
ppasr/model_utils/deepspeech2/__init__.py
ppasr/model_utils/deepspeech2/conv.py
ppasr/model_utils/deepspeech2/encoder.py
ppasr/model_utils/deepspeech2/model.py
ppasr/model_utils/efficient_conformer/__init__.py
ppasr/model_utils/efficient_conformer/attention.py
ppasr/model_utils/efficient_conformer/convolution.py
ppasr/model_utils/efficient_conformer/encoder.py
ppasr/model_utils/efficient_conformer/model.py
ppasr/model_utils/efficient_conformer/subsampling.py
ppasr/model_utils/loss/__init__.py
ppasr/model_utils/loss/ctc.py
ppasr/model_utils/loss/label_smoothing_loss.py
ppasr/model_utils/squeezeformer/__init__.py
ppasr/model_utils/squeezeformer/attention.py
ppasr/model_utils/squeezeformer/conv2d.py
ppasr-3.0.2.dist-info/LICENSE
ppasr-3.0.2.dist-info/METADATA
ppasr-3.0.2.dist-info/WHEEL
ppasr-3.0.2.dist-info/top_level.txt
ppasr-3.0.2.dist-info/RECORD
